gradle.properties
hexdoc_hexchanting/__gradle_version__.py
hexdoc_hexchanting/__init__.py
hexdoc_hexchanting/__version__.py
hexdoc_hexchanting/_hooks.py
hexdoc_hexchanting/py.typed
hexdoc_hexchanting/_export/.gitignore
hexdoc_hexchanting/_export/__init__.py
hexdoc_hexchanting/_export/generated/__init__.py
hexdoc_hexchanting/_export/generated/hexchanting.hexdoc.json
hexdoc_hexchanting/_export/generated/hexchanting.patterns.hexdoc.json
hexdoc_hexchanting/_export/generated/assets/hexcasting/lang/en_us.flatten.json5
hexdoc_hexchanting/_export/generated/assets/hexcasting/patchouli_books/thehexbook/en_us/entries/imbuing.json
hexdoc_hexchanting/_export/generated/assets/hexchanting/lang/en_us.flatten.json5
hexdoc_hexchanting/_export/generated/assets/hexchanting/lang/en_us.json
hexdoc_hexchanting/_export/generated/assets/hexchanting/lang/zh_cn.flatten.json5
hexdoc_hexchanting/_export/generated/assets/hexchanting/lang/zh_cn.json
hexdoc_hexchanting/_export/generated/assets/hexchanting/models/item/amethyst_arrow.json
hexdoc_hexchanting/_export/generated/assets/hexchanting/models/item/amethyst_axe.json
hexdoc_hexchanting/_export/generated/assets/hexchanting/models/item/amethyst_boots.json
hexdoc_hexchanting/_export/generated/assets/hexchanting/models/item/amethyst_boots_amethyst_darker_trim.json
hexdoc_hexchanting/_export/generated/assets/hexchanting/models/item/amethyst_boots_copper_trim.json
hexdoc_hexchanting/_export/generated/assets/hexchanting/models/item/amethyst_boots_diamond_trim.json
hexdoc_hexchanting/_export/generated/assets/hexchanting/models/item/amethyst_boots_emerald_trim.json
hexdoc_hexchanting/_export/generated/assets/hexchanting/models/item/amethyst_boots_gold_trim.json
hexdoc_hexchanting/_export/generated/assets/hexchanting/models/item/amethyst_boots_iron_trim.json
hexdoc_hexchanting/_export/generated/assets/hexchanting/models/item/amethyst_boots_lapis_trim.json
hexdoc_hexchanting-1.1.7.1.0.dist-info/METADATA
hexdoc_hexchanting-1.1.7.1.0.dist-info/WHEEL
hexdoc_hexchanting-1.1.7.1.0.dist-info/entry_points.txt
hexdoc_hexchanting-1.1.7.1.0.dist-info/licenses/LICENSE
hexdoc_hexchanting-1.1.7.1.0.dist-info/RECORD
