Metadata-Version: 2.4
Name: hexdoc-hexchanting
Version: 1.1.7.1.0
Summary: Imbue tools with Hex Casting powers.
Project-URL: Homepage, https://arconyx.github.io/hexchanting/
Project-URL: Source, https://github.com/arconyx/hexchanting
Author: arconyx
License-File: LICENSE
Keywords: hexdoc
Requires-Python: >=3.12
Requires-Dist: hexdoc-hexcasting~=0.11.2.1.0
